{
  "arrivals": [
    {
      "ident": "LV-KCI",
      "ident_icao": null,
      "ident_iata": null,
      "actual_runway_off": "05",
      "actual_runway_on": "19",
      "fa_flight_id": "LVKCI-1764122307-adhoc-1710p",
      "operator": null,
      "operator_icao": null,
      "operator_iata": null,
      "flight_number": null,
      "registration": "LV-KCI",
      "atc_ident": null,
      "inbound_fa_flight_id": "LVKCI-1764115663-adhoc-1047p",
      "codeshares": [],
      "codeshares_iata": [],
      "blocked": false,
      "diverted": false,
      "cancelled": false,
      "position_only": false,
      "origin": {
        "code": "SADF",
        "code_icao": "SADF",
        "code_iata": "QAE",
        "code_lid": null,
        "timezone": "America/Argentina/Buenos_Aires",
        "name": "San Fernando",
        "city": "San Fernando",
        "airport_info_url": "/airports/SADF"
      },
      "destination": {
        "code": "SUMU",
        "code_icao": "SUMU",
        "code_iata": "MVD",
        "code_lid": null,
        "timezone": "America/Montevideo",
        "name": "Carrasco Int'l",
        "city": "Montevideo",
        "airport_info_url": "/airports/SUMU"
      },
      "departure_delay": -164,
      "arrival_delay": -3671,
      "filed_ete": 3507,
      "scheduled_out": null,
      "estimated_out": null,
      "actual_out": null,
      "scheduled_off": "2025-11-26T02:08:21Z",
      "estimated_off": "2025-11-26T02:05:37Z",
      "actual_off": "2025-11-26T02:05:37Z",
      "scheduled_on": "2025-11-26T03:06:48Z",
      "estimated_on": "2025-11-26T03:04:04Z",
      "actual_on": "2025-11-26T02:05:37Z",
      "scheduled_in": null,
      "estimated_in": null,
      "actual_in": null,
      "progress_percent": 100,
      "status": "Estimated arrival",
      "aircraft_type": null,
      "route_distance": 148,
      "filed_airspeed": null,
      "filed_altitude": null,
      "route": null,
      "baggage_claim": null,
      "seats_cabin_business": null,
      "seats_cabin_coach": null,
      "seats_cabin_first": null,
      "gate_origin": null,
      "gate_destination": null,
      "terminal_origin": null,
      "terminal_destination": null,
      "type": "General_Aviation"
    },
    {
      "ident": "CMP125",
      "ident_icao": "CMP125",
      "ident_iata": "CM125",
      "actual_runway_off": "03R",
      "actual_runway_on": "07",
      "fa_flight_id": "CMP125-1763888484-airline-1288p",
      "operator": "CMP",
      "operator_icao": "CMP",
      "operator_iata": "CM",
      "flight_number": "125",
      "registration": "HP-9922CMP",
      "atc_ident": null,
      "inbound_fa_flight_id": "CMP350-1763886094-airline-1150p",
      "codeshares": [],
      "codeshares_iata": [],
      "blocked": false,
      "diverted": false,
      "cancelled": false,
      "position_only": false,
      "origin": {
        "code": "MPTO",
        "code_icao": "MPTO",
        "code_iata": "PTY",
        "code_lid": null,
        "timezone": "America/Panama",
        "name": "Tocumen Int'l",
        "city": "Panama City",
        "airport_info_url": "/airports/MPTO"
      },
      "destination": {
        "code": "SUMU",
        "code_icao": "SUMU",
        "code_iata": "MVD",
        "code_lid": null,
        "timezone": "America/Montevideo",
        "name": "Carrasco Int'l",
        "city": "Montevideo",
        "airport_info_url": "/airports/SUMU"
      },
      "departure_delay": 720,
      "arrival_delay": -840,
      "filed_ete": 24960,
      "scheduled_out": "2025-11-25T17:16:00Z",
      "estimated_out": "2025-11-25T17:22:00Z",
      "actual_out": "2025-11-25T17:28:00Z",
      "scheduled_off": "2025-11-25T17:26:00Z",
      "estimated_off": "2025-11-25T17:46:28Z",
      "actual_off": "2025-11-25T17:46:28Z",
      "scheduled_on": "2025-11-26T00:22:00Z",
      "estimated_on": "2025-11-26T00:13:28Z",
      "actual_on": "2025-11-26T00:13:28Z",
      "scheduled_in": "2025-11-26T00:32:00Z",
      "estimated_in": "2025-11-26T00:13:00Z",
      "actual_in": "2025-11-26T00:18:00Z",
      "progress_percent": 100,
      "status": "Arrived / Gate Arrival",
      "aircraft_type": "B39M",
      "route_distance": 3400,
      "filed_airspeed": 427,
      "filed_altitude": null,
      "route": null,
      "baggage_claim": null,
      "seats_cabin_business": null,
      "seats_cabin_coach": null,
      "seats_cabin_first": null,
      "gate_origin": "219",
      "gate_destination": "32B",
      "terminal_origin": null,
      "terminal_destination": null,
      "type": "Airline"
    },
    {
      "ident": "N680KS",
      "ident_icao": null,
      "ident_iata": null,
      "actual_runway_off": "08",
      "actual_runway_on": "19",
      "fa_flight_id": "N680KS-1764109675-adhoc-1013p",
      "operator": null,
      "operator_icao": null,
      "operator_iata": null,
      "flight_number": null,
      "registration": "N680KS",
      "atc_ident": null,
      "inbound_fa_flight_id": "N680KS-1764100947-adhoc-3621p",
      "codeshares": [],
      "codeshares_iata": [],
      "blocked": false,
      "diverted": false,
      "cancelled": false,
      "position_only": false,
      "origin": {
        "code": "SULS",
        "code_icao": "SULS",
        "code_iata": "PDP",
        "code_lid": null,
        "timezone": "America/Montevideo",
        "name": "Capitan Corbeta CA Curbelo Int'l",
        "city": "Maldonado",
        "airport_info_url": "/airports/SULS"
      },
      "destination": {
        "code": "SUMU",
        "code_icao": "SUMU",
        "code_iata": "MVD",
        "code_lid": null,
        "timezone": "America/Montevideo",
        "name": "Carrasco Int'l",
        "city": "Montevideo",
        "airport_info_url": "/airports/SUMU"
      },
      "departure_delay": -104,
      "arrival_delay": -104,
      "filed_ete": 1081,
      "scheduled_out": null,
      "estimated_out": null,
      "actual_out": null,
      "scheduled_off": "2025-11-25T22:32:50Z",
      "estimated_off": "2025-11-25T22:31:06Z",
      "actual_off": "2025-11-25T22:31:06Z",
      "scheduled_on": "2025-11-25T22:50:51Z",
      "estimated_on": "2025-11-25T22:49:07Z",
      "actual_on": "2025-11-25T22:49:07Z",
      "scheduled_in": null,
      "estimated_in": null,
      "actual_in": null,
      "progress_percent": 100,
      "status": "Arrived",
      "aircraft_type": "C680",
      "route_distance": 53,
      "filed_airspeed": null,
      "filed_altitude": null,
      "route": null,
      "baggage_claim": null,
      "seats_cabin_business": null,
      "seats_cabin_coach": null,
      "seats_cabin_first": null,
      "gate_origin": null,
      "gate_destination": null,
      "terminal_origin": null,
      "terminal_destination": null,
      "type": "General_Aviation"
    },
    {
      "ident": "SKU1801",
      "ident_icao": "SKU1801",
      "ident_iata": "H21801",
      "actual_runway_off": "10",
      "actual_runway_on": "19",
      "fa_flight_id": "SKU1801-1763881168-airline-347p",
      "operator": "SKU",
      "operator_icao": "SKU",
      "operator_iata": "H2",
      "flight_number": "1801",
      "registration": "CC-AZO",
      "atc_ident": null,
      "inbound_fa_flight_id": "SKU1800-1763881168-airline-344p",
      "codeshares": [],
      "codeshares_iata": [],
      "blocked": false,
      "diverted": false,
      "cancelled": false,
      "position_only": false,
      "origin": {
        "code": "SBSV",
        "code_icao": "SBSV",
        "code_iata": "SSA",
        "code_lid": null,
        "timezone": "America/Bahia",
        "name": "Deputado Luis Eduardo Magalhaes Int'l (Dois de Julho)",
        "city": "Salvador",
        "airport_info_url": "/airports/SBSV"
      },
      "destination": {
        "code": "SUMU",
        "code_icao": "SUMU",
        "code_iata": "MVD",
        "code_lid": null,
        "timezone": "America/Montevideo",
        "name": "Carrasco Int'l",
        "city": "Montevideo",
        "airport_info_url": "/airports/SUMU"
      },
      "departure_delay": 6540,
      "arrival_delay": 5820,
      "filed_ete": 20700,
      "scheduled_out": "2025-11-25T16:25:00Z",
      "estimated_out": "2025-11-25T16:25:00Z",
      "actual_out": "2025-11-25T18:14:00Z",
      "scheduled_off": "2025-11-25T16:35:00Z",
      "estimated_off": "2025-11-25T18:29:50Z",
      "actual_off": "2025-11-25T18:29:50Z",
      "scheduled_on": "2025-11-25T22:20:00Z",
      "estimated_on": "2025-11-25T22:31:39Z",
      "actual_on": "2025-11-25T22:31:39Z",
      "scheduled_in": "2025-11-25T21:00:00Z",
      "estimated_in": "2025-11-25T22:42:00Z",
      "actual_in": "2025-11-25T22:37:00Z",
      "progress_percent": 100,
      "status": "Arrived / Delayed",
      "aircraft_type": "A20N",
      "route_distance": 1878,
      "filed_airspeed": 384,
      "filed_altitude": null,
      "route": null,
      "baggage_claim": null,
      "seats_cabin_business": null,
      "seats_cabin_coach": null,
      "seats_cabin_first": null,
      "gate_origin": null,
      "gate_destination": null,
      "terminal_origin": null,
      "terminal_destination": null,
      "type": "Airline"
    },
    {
      "ident": "ARG1388",
      "ident_icao": "ARG1388",
      "ident_iata": "AR1388",
      "actual_runway_off": "13",
      "actual_runway_on": "25",
      "fa_flight_id": "ARG1388-1763884026-airline-926p",
      "operator": "ARG",
      "operator_icao": "ARG",
      "operator_iata": "AR",
      "flight_number": "1388",
      "registration": "LV-CDZ",
      "atc_ident": null,
      "inbound_fa_flight_id": "ARG1733-1763884026-airline-1092p",
      "codeshares": [
        "ITY4673"
      ],
      "codeshares_iata": [
        "AZ4673"
      ],
      "blocked": false,
      "diverted": false,
      "cancelled": false,
      "position_only": false,
      "origin": {
        "code": "SABE",
        "code_icao": "SABE",
        "code_iata": "AEP",
        "code_lid": null,
        "timezone": "America/Argentina/Buenos_Aires",
        "name": "Jorge Newbery",
        "city": "Buenos Aires",
        "airport_info_url": "/airports/SABE"
      },
      "destination": {
        "code": "SUMU",
        "code_icao": "SUMU",
        "code_iata": "MVD",
        "code_lid": null,
        "timezone": "America/Montevideo",
        "name": "Carrasco Int'l",
        "city": "Montevideo",
        "airport_info_url": "/airports/SUMU"
      },
      "departure_delay": 1980,
      "arrival_delay": 1860,
      "filed_ete": 1980,
      "scheduled_out": "2025-11-25T20:45:00Z",
      "estimated_out": "2025-11-25T20:45:00Z",
      "actual_out": "2025-11-25T21:18:00Z",
      "scheduled_off": "2025-11-25T20:53:20Z",
      "estimated_off": "2025-11-25T21:29:00Z",
      "actual_off": "2025-11-25T21:29:00Z",
      "scheduled_on": "2025-11-25T21:26:20Z",
      "estimated_on": "2025-11-25T21:59:00Z",
      "actual_on": "2025-11-25T21:59:00Z",
      "scheduled_in": "2025-11-25T21:35:00Z",
      "estimated_in": "2025-11-25T22:09:40Z",
      "actual_in": "2025-11-25T22:06:00Z",
      "progress_percent": 100,
      "status": "Arrived / Delayed",
      "aircraft_type": "E190",
      "route_distance": 137,
      "filed_airspeed": 215,
      "filed_altitude": null,
      "route": null,
      "baggage_claim": null,
      "seats_cabin_business": null,
      "seats_cabin_coach": null,
      "seats_cabin_first": null,
      "gate_origin": "17",
      "gate_destination": null,
      "terminal_origin": null,
      "terminal_destination": null,
      "type": "Airline"
    },
    {
      "ident": "FAU551",
      "ident_icao": null,
      "ident_iata": null,
      "actual_runway_off": "29L",
      "actual_runway_on": "19",
      "fa_flight_id": "FAU551-1764103265-adhoc-2195p",
      "operator": null,
      "operator_icao": null,
      "operator_iata": null,
      "flight_number": null,
      "registration": null,
      "atc_ident": null,
      "inbound_fa_flight_id": null,
      "codeshares": [],
      "codeshares_iata": [],
      "blocked": false,
      "diverted": false,
      "cancelled": false,
      "position_only": false,
      "origin": {
        "code": "SBBR",
        "code_icao": "SBBR",
        "code_iata": "BSB",
        "code_lid": null,
        "timezone": "America/Sao_Paulo",
        "name": "Presidente Juscelino Kubitschek Int'l",
        "city": "Brasilia",
        "airport_info_url": "/airports/SBBR"
      },
      "destination": {
        "code": "SUMU",
        "code_icao": "SUMU",
        "code_iata": "MVD",
        "code_lid": null,
        "timezone": "America/Montevideo",
        "name": "Carrasco Int'l",
        "city": "Montevideo",
        "airport_info_url": "/airports/SUMU"
      },
      "departure_delay": -637,
      "arrival_delay": -19235,
      "filed_ete": 18598,
      "scheduled_out": null,
      "estimated_out": null,
      "actual_out": null,
      "scheduled_off": "2025-11-25T20:53:00Z",
      "estimated_off": "2025-11-25T20:42:23Z",
      "actual_off": "2025-11-25T20:42:23Z",
      "scheduled_on": "2025-11-26T02:02:58Z",
      "estimated_on": "2025-11-26T01:52:21Z",
      "actual_on": "2025-11-25T20:42:23Z",
      "scheduled_in": null,
      "estimated_in": null,
      "actual_in": null,
      "progress_percent": 100,
      "status": "Estimated arrival",
      "aircraft_type": null,
      "route_distance": 1406,
      "filed_airspeed": null,
      "filed_altitude": null,
      "route": null,
      "baggage_claim": null,
      "seats_cabin_business": null,
      "seats_cabin_coach": null,
      "seats_cabin_first": null,
      "gate_origin": null,
      "gate_destination": null,
      "terminal_origin": null,
      "terminal_destination": null,
      "type": "General_Aviation"
    },
    {
      "ident": "TAM8117",
      "ident_icao": "TAM8117",
      "ident_iata": "JJ8117",
      "actual_runway_off": "17R",
      "actual_runway_on": "19",
      "fa_flight_id": "TAM8117-1763878562-airline-89p",
      "operator": "TAM",
      "operator_icao": "TAM",
      "operator_iata": "JJ",
      "flight_number": "8117",
      "registration": "PT-MXG",
      "atc_ident": null,
      "inbound_fa_flight_id": "TAM8118-1763878562-airline-90p",
      "codeshares": [
        "LAN8117",
        "QFA3932"
      ],
      "codeshares_iata": [
        "LA8117",
        "QF3932"
      ],
      "blocked": false,
      "diverted": false,
      "cancelled": false,
      "position_only": false,
      "origin": {
        "code": "SCEL",
        "code_icao": "SCEL",
        "code_iata": "SCL",
        "code_lid": null,
        "timezone": "America/Santiago",
        "name": "Comodoro Arturo Merino Benitez Int'l",
        "city": "Santiago",
        "airport_info_url": "/airports/SCEL"
      },
      "destination": {
        "code": "SUMU",
        "code_icao": "SUMU",
        "code_iata": "MVD",
        "code_lid": null,
        "timezone": "America/Montevideo",
        "name": "Carrasco Int'l",
        "city": "Montevideo",
        "airport_info_url": "/airports/SUMU"
      },
      "departure_delay": 0,
      "arrival_delay": 240,
      "filed_ete": 6180,
      "scheduled_out": "2025-11-25T18:05:00Z",
      "estimated_out": "2025-11-25T18:05:00Z",
      "actual_out": "2025-11-25T18:05:00Z",
      "scheduled_off": "2025-11-25T18:15:00Z",
      "estimated_off": "2025-11-25T18:24:00Z",
      "actual_off": "2025-11-25T18:24:14Z",
      "scheduled_on": "2025-11-25T19:58:00Z",
      "estimated_on": "2025-11-25T20:15:00Z",
      "actual_on": "2025-11-25T20:15:00Z",
      "scheduled_in": "2025-11-25T20:15:00Z",
      "estimated_in": "2025-11-25T20:23:00Z",
      "actual_in": "2025-11-25T20:19:00Z",
      "progress_percent": 100,
      "status": "Arrived / Gate Arrival",
      "aircraft_type": "A321",
      "route_distance": 850,
      "filed_airspeed": 403,
      "filed_altitude": null,
      "route": null,
      "baggage_claim": null,
      "seats_cabin_business": null,
      "seats_cabin_coach": null,
      "seats_cabin_first": null,
      "gate_origin": null,
      "gate_destination": null,
      "terminal_origin": "2",
      "terminal_destination": null,
      "type": "Airline"
    },
    {
      "ident": "JAT762",
      "ident_icao": "JAT762",
      "ident_iata": "JA762",
      "actual_runway_off": "33",
      "actual_runway_on": "19",
      "fa_flight_id": "JAT762-1763877909-airline-1224p",
      "operator": "JAT",
      "operator_icao": "JAT",
      "operator_iata": "JA",
      "flight_number": "762",
      "registration": "CC-AWS",
      "atc_ident": null,
      "inbound_fa_flight_id": "JAT762-1763877909-airline-1225p",
      "codeshares": [],
      "codeshares_iata": [],
      "blocked": false,
      "diverted": false,
      "cancelled": false,
      "position_only": false,
      "origin": {
        "code": "SBGL",
        "code_icao": "SBGL",
        "code_iata": "GIG",
        "code_lid": null,
        "timezone": "America/Sao_Paulo",
        "name": "Rio de Janeiro/Galeao Intl",
        "city": "Rio de Janeiro",
        "airport_info_url": "/airports/SBGL"
      },
      "destination": {
        "code": "SUMU",
        "code_icao": "SUMU",
        "code_iata": "MVD",
        "code_lid": null,
        "timezone": "America/Montevideo",
        "name": "Carrasco Int'l",
        "city": "Montevideo",
        "airport_info_url": "/airports/SUMU"
      },
      "departure_delay": 360,
      "arrival_delay": -480,
      "filed_ete": 9480,
      "scheduled_out": "2025-11-25T13:00:00Z",
      "estimated_out": "2025-11-25T13:08:00Z",
      "actual_out": "2025-11-25T13:06:00Z",
      "scheduled_off": "2025-11-25T13:10:00Z",
      "estimated_off": "2025-11-25T13:19:09Z",
      "actual_off": "2025-11-25T13:19:09Z",
      "scheduled_on": "2025-11-25T15:48:00Z",
      "estimated_on": "2025-11-25T15:52:12Z",
      "actual_on": "2025-11-25T15:52:12Z",
      "scheduled_in": "2025-11-25T16:06:00Z",
      "estimated_in": "2025-11-25T15:55:00Z",
      "actual_in": "2025-11-25T15:58:00Z",
      "progress_percent": 100,
      "status": "Arrived / Gate Arrival",
      "aircraft_type": "A321",
      "route_distance": 1135,
      "filed_airspeed": 357,
      "filed_altitude": null,
      "route": null,
      "baggage_claim": null,
      "seats_cabin_business": null,
      "seats_cabin_coach": null,
      "seats_cabin_first": null,
      "gate_origin": "C56",
      "gate_destination": null,
      "terminal_origin": "2",
      "terminal_destination": null,
      "type": "Airline"
    },
    {
      "ident": "ARG1384",
      "ident_icao": "ARG1384",
      "ident_iata": "AR1384",
      "actual_runway_off": "13",
      "actual_runway_on": "07",
      "fa_flight_id": "ARG1384-1763884026-airline-924p",
      "operator": "ARG",
      "operator_icao": "ARG",
      "operator_iata": "AR",
      "flight_number": "1384",
      "registration": "LV-BYY",
      "atc_ident": null,
      "inbound_fa_flight_id": "ARG1883-1763793254-airline-1121p",
      "codeshares": [],
      "codeshares_iata": [],
      "blocked": false,
      "diverted": false,
      "cancelled": false,
      "position_only": false,
      "origin": {
        "code": "SABE",
        "code_icao": "SABE",
        "code_iata": "AEP",
        "code_lid": null,
        "timezone": "America/Argentina/Buenos_Aires",
        "name": "Jorge Newbery",
        "city": "Buenos Aires",
        "airport_info_url": "/airports/SABE"
      },
      "destination": {
        "code": "SUMU",
        "code_icao": "SUMU",
        "code_iata": "MVD",
        "code_lid": null,
        "timezone": "America/Montevideo",
        "name": "Carrasco Int'l",
        "city": "Montevideo",
        "airport_info_url": "/airports/SUMU"
      },
      "departure_delay": 900,
      "arrival_delay": 1080,
      "filed_ete": 1860,
      "scheduled_out": "2025-11-25T14:35:00Z",
      "estimated_out": "2025-11-25T14:45:00Z",
      "actual_out": "2025-11-25T14:50:00Z",
      "scheduled_off": "2025-11-25T14:43:20Z",
      "estimated_off": "2025-11-25T15:08:45Z",
      "actual_off": "2025-11-25T15:08:45Z",
      "scheduled_on": "2025-11-25T15:14:20Z",
      "estimated_on": "2025-11-25T15:34:46Z",
      "actual_on": "2025-11-25T15:34:46Z",
      "scheduled_in": "2025-11-25T15:25:00Z",
      "estimated_in": "2025-11-25T15:40:00Z",
      "actual_in": "2025-11-25T15:43:00Z",
      "progress_percent": 100,
      "status": "Arrived / Gate Arrival",
      "aircraft_type": "B737",
      "route_distance": 137,
      "filed_airspeed": 215,
      "filed_altitude": null,
      "route": null,
      "baggage_claim": null,
      "seats_cabin_business": null,
      "seats_cabin_coach": null,
      "seats_cabin_first": null,
      "gate_origin": "17",
      "gate_destination": null,
      "terminal_origin": null,
      "terminal_destination": null,
      "type": "Airline"
    },
    {
      "ident": "F595",
      "ident_icao": null,
      "ident_iata": null,
      "actual_runway_off": "07",
      "actual_runway_on": "19",
      "fa_flight_id": "F595-1764084771-adhoc-3186p",
      "operator": null,
      "operator_icao": null,
      "operator_iata": null,
      "flight_number": null,
      "registration": null,
      "atc_ident": null,
      "inbound_fa_flight_id": null,
      "codeshares": [],
      "codeshares_iata": [],
      "blocked": false,
      "diverted": false,
      "cancelled": false,
      "position_only": false,
      "origin": {
        "code": "SUMU",
        "code_icao": "SUMU",
        "code_iata": "MVD",
        "code_lid": null,
        "timezone": "America/Montevideo",
        "name": "Carrasco Int'l",
        "city": "Montevideo",
        "airport_info_url": "/airports/SUMU"
      },
      "destination": {
        "code": "SUMU",
        "code_icao": "SUMU",
        "code_iata": "MVD",
        "code_lid": null,
        "timezone": "America/Montevideo",
        "name": "Carrasco Int'l",
        "city": "Montevideo",
        "airport_info_url": "/airports/SUMU"
      },
      "departure_delay": 0,
      "arrival_delay": -4792,
      "filed_ete": 4792,
      "scheduled_out": null,
      "estimated_out": null,
      "actual_out": null,
      "scheduled_off": "2025-11-25T15:32:35Z",
      "estimated_off": "2025-11-25T15:32:35Z",
      "actual_off": "2025-11-25T15:32:35Z",
      "scheduled_on": "2025-11-25T16:52:27Z",
      "estimated_on": "2025-11-25T16:52:27Z",
      "actual_on": "2025-11-25T15:32:35Z",
      "scheduled_in": null,
      "estimated_in": null,
      "actual_in": null,
      "progress_percent": 100,
      "status": "Estimated arrival",
      "aircraft_type": null,
      "route_distance": 0,
      "filed_airspeed": null,
      "filed_altitude": null,
      "route": null,
      "baggage_claim": null,
      "seats_cabin_business": null,
      "seats_cabin_coach": null,
      "seats_cabin_first": null,
      "gate_origin": null,
      "gate_destination": null,
      "terminal_origin": null,
      "terminal_destination": null,
      "type": "General_Aviation"
    },
    {
      "ident": "CX-IPR",
      "ident_icao": null,
      "ident_iata": null,
      "actual_runway_off": "01",
      "actual_runway_on": "19",
      "fa_flight_id": "CXIPR-1764079460-adhoc-1015p",
      "operator": null,
      "operator_icao": null,
      "operator_iata": null,
      "flight_number": null,
      "registration": "CX-IPR",
      "atc_ident": null,
      "inbound_fa_flight_id": "CXIPR-1764073959-adhoc-0p",
      "codeshares": [],
      "codeshares_iata": [],
      "blocked": false,
      "diverted": false,
      "cancelled": false,
      "position_only": false,
      "origin": {
        "code": "SUMU",
        "code_icao": "SUMU",
        "code_iata": "MVD",
        "code_lid": null,
        "timezone": "America/Montevideo",
        "name": "Carrasco Int'l",
        "city": "Montevideo",
        "airport_info_url": "/airports/SUMU"
      },
      "destination": {
        "code": "SUMU",
        "code_icao": "SUMU",
        "code_iata": "MVD",
        "code_lid": null,
        "timezone": "America/Montevideo",
        "name": "Carrasco Int'l",
        "city": "Montevideo",
        "airport_info_url": "/airports/SUMU"
      },
      "departure_delay": 0,
      "arrival_delay": 0,
      "filed_ete": 4707,
      "scheduled_out": null,
      "estimated_out": null,
      "actual_out": null,
      "scheduled_off": "2025-11-25T14:04:14Z",
      "estimated_off": "2025-11-25T14:04:14Z",
      "actual_off": "2025-11-25T14:04:14Z",
      "scheduled_on": "2025-11-25T15:22:41Z",
      "estimated_on": "2025-11-25T15:22:41Z",
      "actual_on": "2025-11-25T15:22:41Z",
      "scheduled_in": null,
      "estimated_in": null,
      "actual_in": null,
      "progress_percent": 100,
      "status": "Arrived",
      "aircraft_type": null,
      "route_distance": 0,
      "filed_airspeed": null,
      "filed_altitude": null,
      "route": null,
      "baggage_claim": null,
      "seats_cabin_business": null,
      "seats_cabin_coach": null,
      "seats_cabin_first": null,
      "gate_origin": null,
      "gate_destination": null,
      "terminal_origin": null,
      "terminal_destination": null,
      "type": "General_Aviation"
    },
    {
      "ident": "GLO7630",
      "ident_icao": "GLO7630",
      "ident_iata": "G37630",
      "actual_runway_off": "10L",
      "actual_runway_on": "07",
      "fa_flight_id": "GLO7630-1763879736-airline-1137p",
      "operator": "GLO",
      "operator_icao": "GLO",
      "operator_iata": "G3",
      "flight_number": "7630",
      "registration": "PS-GPL",
      "atc_ident": null,
      "inbound_fa_flight_id": "GLO1631-1763877159-schedule-50p",
      "codeshares": [
        "AAL7746",
        "ACA9829",
        "AFR6332",
        "AMX8069",
        "KLM9402",
        "THY9478",
        "UAE3733"
      ],
      "codeshares_iata": [
        "AA7746",
        "AC9829",
        "AF6332",
        "AM8069",
        "KL9402",
        "TK9478",
        "EK3733"
      ],
      "blocked": false,
      "diverted": false,
      "cancelled": false,
      "position_only": false,
      "origin": {
        "code": "SBGR",
        "code_icao": "SBGR",
        "code_iata": "GRU",
        "code_lid": null,
        "timezone": "America/Sao_Paulo",
        "name": "São Paulo-Guarulhos Int'l",
        "city": "Sao Paulo",
        "airport_info_url": "/airports/SBGR"
      },
      "destination": {
        "code": "SUMU",
        "code_icao": "SUMU",
        "code_iata": "MVD",
        "code_lid": null,
        "timezone": "America/Montevideo",
        "name": "Carrasco Int'l",
        "city": "Montevideo",
        "airport_info_url": "/airports/SUMU"
      },
      "departure_delay": 0,
      "arrival_delay": 240,
      "filed_ete": 8700,
      "scheduled_out": "2025-11-25T12:20:00Z",
      "estimated_out": "2025-11-25T12:20:00Z",
      "actual_out": null,
      "scheduled_off": "2025-11-25T12:30:00Z",
      "estimated_off": "2025-11-25T12:39:04Z",
      "actual_off": "2025-11-25T12:39:04Z",
      "scheduled_on": "2025-11-25T14:55:00Z",
      "estimated_on": "2025-11-25T14:59:00Z",
      "actual_on": "2025-11-25T14:54:50Z",
      "scheduled_in": "2025-11-25T15:05:00Z",
      "estimated_in": "2025-11-25T15:09:00Z",
      "actual_in": null,
      "progress_percent": 100,
      "status": "Arrived / Gate Arrival",
      "aircraft_type": "B38M",
      "route_distance": 977,
      "filed_airspeed": 352,
      "filed_altitude": null,
      "route": null,
      "baggage_claim": null,
      "seats_cabin_business": null,
      "seats_cabin_coach": null,
      "seats_cabin_first": null,
      "gate_origin": "311",
      "gate_destination": null,
      "terminal_origin": "3",
      "terminal_destination": null,
      "type": "Airline"
    },
    {
      "ident": "TAM8118",
      "ident_icao": "TAM8118",
      "ident_iata": "JJ8118",
      "actual_runway_off": "10L",
      "actual_runway_on": "07",
      "fa_flight_id": "TAM8118-1763878562-airline-91p",
      "operator": "TAM",
      "operator_icao": "TAM",
      "operator_iata": "JJ",
      "flight_number": "8118",
      "registration": "PT-MXG",
      "atc_ident": null,
      "inbound_fa_flight_id": "TAM3561-1763877565-airline-581p",
      "codeshares": [
        "DAL7383",
        "DLH4694",
        "IBE6537",
        "LAN8118",
        "QTR5195",
        "SWR9718"
      ],
      "codeshares_iata": [
        "DL7383",
        "LH4694",
        "IB6537",
        "LA8118",
        "QR5195",
        "LX9718"
      ],
      "blocked": false,
      "diverted": false,
      "cancelled": false,
      "position_only": false,
      "origin": {
        "code": "SBGR",
        "code_icao": "SBGR",
        "code_iata": "GRU",
        "code_lid": null,
        "timezone": "America/Sao_Paulo",
        "name": "São Paulo-Guarulhos Int'l",
        "city": "Sao Paulo",
        "airport_info_url": "/airports/SBGR"
      },
      "destination": {
        "code": "SUMU",
        "code_icao": "SUMU",
        "code_iata": "MVD",
        "code_lid": null,
        "timezone": "America/Montevideo",
        "name": "Carrasco Int'l",
        "city": "Montevideo",
        "airport_info_url": "/airports/SUMU"
      },
      "departure_delay": -420,
      "arrival_delay": -780,
      "filed_ete": 7680,
      "scheduled_out": "2025-11-25T10:55:00Z",
      "estimated_out": "2025-11-25T10:55:00Z",
      "actual_out": "2025-11-25T10:48:00Z",
      "scheduled_off": "2025-11-25T11:05:00Z",
      "estimated_off": "2025-11-25T11:01:14Z",
      "actual_off": "2025-11-25T11:01:14Z",
      "scheduled_on": "2025-11-25T13:13:00Z",
      "estimated_on": "2025-11-25T13:19:00Z",
      "actual_on": "2025-11-25T13:19:00Z",
      "scheduled_in": "2025-11-25T13:35:00Z",
      "estimated_in": "2025-11-25T13:26:00Z",
      "actual_in": "2025-11-25T13:22:00Z",
      "progress_percent": 100,
      "status": "Arrived / Gate Arrival",
      "aircraft_type": "A321",
      "route_distance": 977,
      "filed_airspeed": 364,
      "filed_altitude": null,
      "route": null,
      "baggage_claim": null,
      "seats_cabin_business": null,
      "seats_cabin_coach": null,
      "seats_cabin_first": null,
      "gate_origin": "311",
      "gate_destination": null,
      "terminal_origin": "3",
      "terminal_destination": null,
      "type": "Airline"
    },
    {
      "ident": "CX-IPR",
      "ident_icao": null,
      "ident_iata": null,
      "actual_runway_off": "01",
      "actual_runway_on": "07",
      "fa_flight_id": "CXIPR-1764073959-adhoc-0p",
      "operator": null,
      "operator_icao": null,
      "operator_iata": null,
      "flight_number": null,
      "registration": "CX-IPR",
      "atc_ident": null,
      "inbound_fa_flight_id": "CXIPR-1764070723-adhoc-366p",
      "codeshares": [],
      "codeshares_iata": [],
      "blocked": false,
      "diverted": false,
      "cancelled": false,
      "position_only": false,
      "origin": {
        "code": "SUMU",
        "code_icao": "SUMU",
        "code_iata": "MVD",
        "code_lid": null,
        "timezone": "America/Montevideo",
        "name": "Carrasco Int'l",
        "city": "Montevideo",
        "airport_info_url": "/airports/SUMU"
      },
      "destination": {
        "code": "SUMU",
        "code_icao": "SUMU",
        "code_iata": "MVD",
        "code_lid": null,
        "timezone": "America/Montevideo",
        "name": "Carrasco Int'l",
        "city": "Montevideo",
        "airport_info_url": "/airports/SUMU"
      },
      "departure_delay": 12,
      "arrival_delay": -236,
      "filed_ete": 248,
      "scheduled_out": null,
      "estimated_out": null,
      "actual_out": null,
      "scheduled_off": "2025-11-25T12:32:36Z",
      "estimated_off": "2025-11-25T12:32:48Z",
      "actual_off": "2025-11-25T12:32:48Z",
      "scheduled_on": "2025-11-25T12:36:44Z",
      "estimated_on": "2025-11-25T12:36:56Z",
      "actual_on": "2025-11-25T12:32:48Z",
      "scheduled_in": null,
      "estimated_in": null,
      "actual_in": null,
      "progress_percent": 100,
      "status": "Estimated arrival",
      "aircraft_type": null,
      "route_distance": 0,
      "filed_airspeed": null,
      "filed_altitude": null,
      "route": null,
      "baggage_claim": null,
      "seats_cabin_business": null,
      "seats_cabin_coach": null,
      "seats_cabin_first": null,
      "gate_origin": null,
      "gate_destination": null,
      "terminal_origin": null,
      "terminal_destination": null,
      "type": "General_Aviation"
    },
    {
      "ident": "AEA45",
      "ident_icao": "AEA45",
      "ident_iata": "UX45",
      "actual_runway_off": "36R",
      "actual_runway_on": "07",
      "fa_flight_id": "AEA45-1763792430-airline-1034p",
      "operator": "AEA",
      "operator_icao": "AEA",
      "operator_iata": "UX",
      "flight_number": "45",
      "registration": "EC-OGY",
      "atc_ident": null,
      "inbound_fa_flight_id": "AEA7708-1763793869-airline-625p",
      "codeshares": [],
      "codeshares_iata": [],
      "blocked": false,
      "diverted": false,
      "cancelled": false,
      "position_only": false,
      "origin": {
        "code": "LEMD",
        "code_icao": "LEMD",
        "code_iata": "MAD",
        "code_lid": null,
        "timezone": "Europe/Madrid",
        "name": "Adolfo Suárez Madrid-Barajas",
        "city": "Madrid",
        "airport_info_url": "/airports/LEMD"
      },
      "destination": {
        "code": "SUMU",
        "code_icao": "SUMU",
        "code_iata": "MVD",
        "code_lid": null,
        "timezone": "America/Montevideo",
        "name": "Carrasco Int'l",
        "city": "Montevideo",
        "airport_info_url": "/airports/SUMU"
      },
      "departure_delay": 3360,
      "arrival_delay": 2460,
      "filed_ete": 40740,
      "scheduled_out": "2025-11-24T22:45:00Z",
      "estimated_out": "2025-11-24T23:45:00Z",
      "actual_out": "2025-11-24T23:41:00Z",
      "scheduled_off": "2025-11-24T22:55:00Z",
      "estimated_off": "2025-11-25T00:02:20Z",
      "actual_off": "2025-11-25T00:02:20Z",
      "scheduled_on": "2025-11-25T10:14:00Z",
      "estimated_on": "2025-11-25T12:02:00Z",
      "actual_on": "2025-11-25T12:02:00Z",
      "scheduled_in": "2025-11-25T11:25:00Z",
      "estimated_in": "2025-11-25T11:51:00Z",
      "actual_in": "2025-11-25T12:06:00Z",
      "progress_percent": 100,
      "status": "Arrived / Delayed",
      "aircraft_type": "B789",
      "route_distance": 6188,
      "filed_airspeed": 437,
      "filed_altitude": null,
      "route": null,
      "baggage_claim": null,
      "seats_cabin_business": null,
      "seats_cabin_coach": null,
      "seats_cabin_first": null,
      "gate_origin": "B23",
      "gate_destination": null,
      "terminal_origin": "1",
      "terminal_destination": null,
      "type": "Airline"
    }
  ],
  "departures": [
    {
      "ident": "N680KS",
      "ident_icao": null,
      "ident_iata": null,
      "actual_runway_off": "19",
      "actual_runway_on": "20",
      "fa_flight_id": "N680KS-1764114627-adhoc-3936p",
      "operator": null,
      "operator_icao": null,
      "operator_iata": null,
      "flight_number": null,
      "registration": "N680KS",
      "atc_ident": null,
      "inbound_fa_flight_id": "N680KS-1764109675-adhoc-1013p",
      "codeshares": [],
      "codeshares_iata": [],
      "blocked": false,
      "diverted": false,
      "cancelled": false,
      "position_only": false,
      "origin": {
        "code": "SUMU",
        "code_icao": "SUMU",
        "code_iata": "MVD",
        "code_lid": null,
        "timezone": "America/Montevideo",
        "name": "Carrasco Int'l",
        "city": "Montevideo",
        "airport_info_url": "/airports/SUMU"
      },
      "destination": {
        "code": "SGAM",
        "code_icao": "SGAM",
        "code_iata": null,
        "code_lid": null,
        "timezone": "America/Asuncion",
        "name": "Luque/Nu Guazu Airport",
        "city": "Campo Grande",
        "airport_info_url": "/airports/SGAM"
      },
      "departure_delay": -11,
      "arrival_delay": 0,
      "filed_ete": 5341,
      "scheduled_out": null,
      "estimated_out": null,
      "actual_out": null,
      "scheduled_off": "2025-11-25T23:58:12Z",
      "estimated_off": "2025-11-25T23:58:12Z",
      "actual_off": "2025-11-25T23:58:01Z",
      "scheduled_on": "2025-11-26T01:27:13Z",
      "estimated_on": "2025-11-26T01:27:13Z",
      "actual_on": "2025-11-26T01:27:13Z",
      "scheduled_in": null,
      "estimated_in": null,
      "actual_in": null,
      "progress_percent": 100,
      "status": "Arrived",
      "aircraft_type": "C680",
      "route_distance": 668,
      "filed_airspeed": null,
      "filed_altitude": null,
      "route": null,
      "baggage_claim": null,
      "seats_cabin_business": null,
      "seats_cabin_coach": null,
      "seats_cabin_first": null,
      "gate_origin": null,
      "gate_destination": null,
      "terminal_origin": null,
      "terminal_destination": null,
      "type": "General_Aviation"
    },
    {
      "ident": "CX-MAS",
      "ident_icao": null,
      "ident_iata": null,
      "actual_runway_off": "19",
      "actual_runway_on": "11",
      "fa_flight_id": "CXMAS-1764114274-adhoc-3696p",
      "operator": null,
      "operator_icao": null,
      "operator_iata": null,
      "flight_number": null,
      "registration": "CX-MAS",
      "atc_ident": null,
      "inbound_fa_flight_id": "CXMAS-1764070307-adhoc-2367p",
      "codeshares": [],
      "codeshares_iata": [],
      "blocked": false,
      "diverted": false,
      "cancelled": false,
      "position_only": false,
      "origin": {
        "code": "SUMU",
        "code_icao": "SUMU",
        "code_iata": "MVD",
        "code_lid": null,
        "timezone": "America/Montevideo",
        "name": "Carrasco Int'l",
        "city": "Montevideo",
        "airport_info_url": "/airports/SUMU"
      },
      "destination": {
        "code": "SAEZ",
        "code_icao": "SAEZ",
        "code_iata": "EZE",
        "code_lid": null,
        "timezone": "America/Argentina/Buenos_Aires",
        "name": "Ministro Pistarini Int'l",
        "city": "Ezeiza",
        "airport_info_url": "/airports/SAEZ"
      },
      "departure_delay": 0,
      "arrival_delay": 0,
      "filed_ete": 3102,
      "scheduled_out": null,
      "estimated_out": null,
      "actual_out": null,
      "scheduled_off": "2025-11-25T23:44:40Z",
      "estimated_off": "2025-11-25T23:44:40Z",
      "actual_off": "2025-11-25T23:44:40Z",
      "scheduled_on": "2025-11-26T00:36:22Z",
      "estimated_on": "2025-11-26T00:36:22Z",
      "actual_on": "2025-11-26T00:36:22Z",
      "scheduled_in": null,
      "estimated_in": null,
      "actual_in": null,
      "progress_percent": 100,
      "status": "Arrived",
      "aircraft_type": null,
      "route_distance": 142,
      "filed_airspeed": null,
      "filed_altitude": null,
      "route": null,
      "baggage_claim": null,
      "seats_cabin_business": null,
      "seats_cabin_coach": null,
      "seats_cabin_first": null,
      "gate_origin": null,
      "gate_destination": null,
      "terminal_origin": null,
      "terminal_destination": null,
      "type": "General_Aviation"
    },
    {
      "ident": "SKU1801",
      "ident_icao": "SKU1801",
      "ident_iata": "H21801",
      "actual_runway_off": "25",
      "actual_runway_on": "17R",
      "fa_flight_id": "SKU1801-1763881168-airline-346p",
      "operator": "SKU",
      "operator_icao": "SKU",
      "operator_iata": "H2",
      "flight_number": "1801",
      "registration": "CC-AZO",
      "atc_ident": null,
      "inbound_fa_flight_id": "SKU1800-1763881168-airline-345p",
      "codeshares": [],
      "codeshares_iata": [],
      "blocked": false,
      "diverted": false,
      "cancelled": false,
      "position_only": false,
      "origin": {
        "code": "SUMU",
        "code_icao": "SUMU",
        "code_iata": "MVD",
        "code_lid": null,
        "timezone": "America/Montevideo",
        "name": "Carrasco Int'l",
        "city": "Montevideo",
        "airport_info_url": "/airports/SUMU"
      },
      "destination": {
        "code": "SCEL",
        "code_icao": "SCEL",
        "code_iata": "SCL",
        "code_lid": null,
        "timezone": "America/Santiago",
        "name": "Comodoro Arturo Merino Benitez Int'l",
        "city": "Santiago",
        "airport_info_url": "/airports/SCEL"
      },
      "departure_delay": 5280,
      "arrival_delay": 3960,
      "filed_ete": 8400,
      "scheduled_out": "2025-11-25T22:00:00Z",
      "estimated_out": "2025-11-25T23:40:00Z",
      "actual_out": "2025-11-25T23:28:00Z",
      "scheduled_off": "2025-11-25T22:10:00Z",
      "estimated_off": "2025-11-25T23:39:56Z",
      "actual_off": "2025-11-25T23:39:56Z",
      "scheduled_on": "2025-11-26T00:30:00Z",
      "estimated_on": "2025-11-26T01:38:55Z",
      "actual_on": "2025-11-26T01:38:55Z",
      "scheduled_in": "2025-11-26T00:45:00Z",
      "estimated_in": "2025-11-26T01:51:00Z",
      "actual_in": null,
      "progress_percent": 100,
      "status": "Arrived / Gate Arrival",
      "aircraft_type": "A20N",
      "route_distance": 850,
      "filed_airspeed": 306,
      "filed_altitude": null,
      "route": null,
      "baggage_claim": null,
      "seats_cabin_business": null,
      "seats_cabin_coach": null,
      "seats_cabin_first": null,
      "gate_origin": null,
      "gate_destination": null,
      "terminal_origin": null,
      "terminal_destination": "2",
      "type": "Airline"
    },
    {
      "ident": "LV-KCI",
      "ident_icao": null,
      "ident_iata": null,
      "actual_runway_off": null,
      "actual_runway_on": "08",
      "fa_flight_id": "LVKCI-1764111634-adhoc-1747p",
      "operator": null,
      "operator_icao": null,
      "operator_iata": null,
      "flight_number": null,
      "registration": "LV-KCI",
      "atc_ident": null,
      "inbound_fa_flight_id": "LVKCI-1764024083-adhoc-1333p",
      "codeshares": [],
      "codeshares_iata": [],
      "blocked": false,
      "diverted": false,
      "cancelled": false,
      "position_only": false,
      "origin": {
        "code": "SUMU",
        "code_icao": "SUMU",
        "code_iata": "MVD",
        "code_lid": null,
        "timezone": "America/Montevideo",
        "name": "Carrasco Int'l",
        "city": "Montevideo",
        "airport_info_url": "/airports/SUMU"
      },
      "destination": {
        "code": "SULS",
        "code_icao": "SULS",
        "code_iata": "PDP",
        "code_lid": null,
        "timezone": "America/Montevideo",
        "name": "Capitan Corbeta CA Curbelo Int'l",
        "city": "Maldonado",
        "airport_info_url": "/airports/SULS"
      },
      "departure_delay": -166,
      "arrival_delay": 0,
      "filed_ete": 1314,
      "scheduled_out": null,
      "estimated_out": null,
      "actual_out": null,
      "scheduled_off": "2025-11-25T23:08:18Z",
      "estimated_off": "2025-11-25T23:08:18Z",
      "actual_off": "2025-11-25T23:05:32Z",
      "scheduled_on": "2025-11-25T23:30:12Z",
      "estimated_on": "2025-11-25T23:30:12Z",
      "actual_on": "2025-11-25T23:30:12Z",
      "scheduled_in": null,
      "estimated_in": null,
      "actual_in": null,
      "progress_percent": 100,
      "status": "Arrived",
      "aircraft_type": null,
      "route_distance": 53,
      "filed_airspeed": null,
      "filed_altitude": null,
      "route": null,
      "baggage_claim": null,
      "seats_cabin_business": null,
      "seats_cabin_coach": null,
      "seats_cabin_first": null,
      "gate_origin": null,
      "gate_destination": null,
      "terminal_origin": null,
      "terminal_destination": null,
      "type": "General_Aviation"
    },
    {
      "ident": "ARG1389",
      "ident_icao": "ARG1389",
      "ident_iata": "AR1389",
      "actual_runway_off": null,
      "actual_runway_on": "13",
      "fa_flight_id": "ARG1389-1763884026-airline-927p",
      "operator": "ARG",
      "operator_icao": "ARG",
      "operator_iata": "AR",
      "flight_number": "1389",
      "registration": "LV-CDZ",
      "atc_ident": null,
      "inbound_fa_flight_id": "ARG1388-1763884026-airline-926p",
      "codeshares": [
        "KLM9226"
      ],
      "codeshares_iata": [
        "KL9226"
      ],
      "blocked": false,
      "diverted": false,
      "cancelled": false,
      "position_only": false,
      "origin": {
        "code": "SUMU",
        "code_icao": "SUMU",
        "code_iata": "MVD",
        "code_lid": null,
        "timezone": "America/Montevideo",
        "name": "Carrasco Int'l",
        "city": "Montevideo",
        "airport_info_url": "/airports/SUMU"
      },
      "destination": {
        "code": "SABE",
        "code_icao": "SABE",
        "code_iata": "AEP",
        "code_lid": null,
        "timezone": "America/Argentina/Buenos_Aires",
        "name": "Jorge Newbery",
        "city": "Buenos Aires",
        "airport_info_url": "/airports/SABE"
      },
      "departure_delay": 1020,
      "arrival_delay": 600,
      "filed_ete": 2160,
      "scheduled_out": "2025-11-25T22:25:00Z",
      "estimated_out": "2025-11-25T22:25:00Z",
      "actual_out": "2025-11-25T22:42:00Z",
      "scheduled_off": "2025-11-25T22:34:10Z",
      "estimated_off": "2025-11-25T22:53:00Z",
      "actual_off": "2025-11-25T22:53:00Z",
      "scheduled_on": "2025-11-25T23:10:10Z",
      "estimated_on": "2025-11-25T23:25:00Z",
      "actual_on": "2025-11-25T23:25:00Z",
      "scheduled_in": "2025-11-25T23:20:00Z",
      "estimated_in": "2025-11-25T23:37:50Z",
      "actual_in": "2025-11-25T23:30:00Z",
      "progress_percent": 100,
      "status": "Arrived / Gate Arrival",
      "aircraft_type": "E190",
      "route_distance": 137,
      "filed_airspeed": 195,
      "filed_altitude": null,
      "route": null,
      "baggage_claim": null,
      "seats_cabin_business": null,
      "seats_cabin_coach": null,
      "seats_cabin_first": null,
      "gate_origin": null,
      "gate_destination": null,
      "terminal_origin": null,
      "terminal_destination": null,
      "type": "Airline"
    },
    {
      "ident": "TAM8117",
      "ident_icao": "TAM8117",
      "ident_iata": "JJ8117",
      "actual_runway_off": "07",
      "actual_runway_on": "10R",
      "fa_flight_id": "TAM8117-1763877565-airline-628p",
      "operator": "TAM",
      "operator_icao": "TAM",
      "operator_iata": "JJ",
      "flight_number": "8117",
      "registration": "PT-MXG",
      "atc_ident": null,
      "inbound_fa_flight_id": "TAM8117-1763878562-airline-89p",
      "codeshares": [
        "AMX8575",
        "DAL6734",
        "DAL7365",
        "IBE6538",
        "IBE6610",
        "LAN8117",
        "QTR5191"
      ],
      "codeshares_iata": [
        "AM8575",
        "DL6734",
        "DL7365",
        "IB6538",
        "IB6610",
        "LA8117",
        "QR5191"
      ],
      "blocked": false,
      "diverted": false,
      "cancelled": false,
      "position_only": false,
      "origin": {
        "code": "SUMU",
        "code_icao": "SUMU",
        "code_iata": "MVD",
        "code_lid": null,
        "timezone": "America/Montevideo",
        "name": "Carrasco Int'l",
        "city": "Montevideo",
        "airport_info_url": "/airports/SUMU"
      },
      "destination": {
        "code": "SBGR",
        "code_icao": "SBGR",
        "code_iata": "GRU",
        "code_lid": null,
        "timezone": "America/Sao_Paulo",
        "name": "São Paulo-Guarulhos Int'l",
        "city": "Sao Paulo",
        "airport_info_url": "/airports/SBGR"
      },
      "departure_delay": 180,
      "arrival_delay": 180,
      "filed_ete": 8220,
      "scheduled_out": "2025-11-25T21:15:00Z",
      "estimated_out": "2025-11-25T21:15:00Z",
      "actual_out": "2025-11-25T21:18:00Z",
      "scheduled_off": "2025-11-25T21:25:00Z",
      "estimated_off": "2025-11-25T21:32:41Z",
      "actual_off": "2025-11-25T21:32:41Z",
      "scheduled_on": "2025-11-25T23:42:00Z",
      "estimated_on": "2025-11-25T23:51:18Z",
      "actual_on": "2025-11-25T23:51:18Z",
      "scheduled_in": "2025-11-25T23:55:00Z",
      "estimated_in": "2025-11-25T23:56:00Z",
      "actual_in": "2025-11-25T23:58:00Z",
      "progress_percent": 100,
      "status": "Arrived / Gate Arrival",
      "aircraft_type": "A321",
      "route_distance": 977,
      "filed_airspeed": 364,
      "filed_altitude": null,
      "route": null,
      "baggage_claim": null,
      "seats_cabin_business": null,
      "seats_cabin_coach": null,
      "seats_cabin_first": null,
      "gate_origin": null,
      "gate_destination": null,
      "terminal_origin": null,
      "terminal_destination": "3",
      "type": "Airline"
    },
    {
      "ident": "IBE170",
      "ident_icao": "IBE170",
      "ident_iata": "IB170",
      "actual_runway_off": "25",
      "actual_runway_on": null,
      "fa_flight_id": "IBE170-1763880398-airline-918p",
      "operator": "IBE",
      "operator_icao": "IBE",
      "operator_iata": "IB",
      "flight_number": "170",
      "registration": "EC-MLB",
      "atc_ident": null,
      "inbound_fa_flight_id": "IBE169-1763802347-airline-985p",
      "codeshares": [
        "BAW4212",
        "QTR5059"
      ],
      "codeshares_iata": [
        "BA4212",
        "QR5059"
      ],
      "blocked": false,
      "diverted": false,
      "cancelled": false,
      "position_only": false,
      "origin": {
        "code": "SUMU",
        "code_icao": "SUMU",
        "code_iata": "MVD",
        "code_lid": null,
        "timezone": "America/Montevideo",
        "name": "Carrasco Int'l",
        "city": "Montevideo",
        "airport_info_url": "/airports/SUMU"
      },
      "destination": {
        "code": "LEMD",
        "code_icao": "LEMD",
        "code_iata": "MAD",
        "code_lid": null,
        "timezone": "Europe/Madrid",
        "name": "Adolfo Suárez Madrid-Barajas",
        "city": "Madrid",
        "airport_info_url": "/airports/LEMD"
      },
      "departure_delay": -600,
      "arrival_delay": -1432,
      "filed_ete": 42060,
      "scheduled_out": "2025-11-25T17:15:00Z",
      "estimated_out": "2025-11-25T17:15:00Z",
      "actual_out": "2025-11-25T17:05:00Z",
      "scheduled_off": "2025-11-25T17:25:00Z",
      "estimated_off": "2025-11-25T17:17:17Z",
      "actual_off": "2025-11-25T17:17:17Z",
      "scheduled_on": "2025-11-26T05:06:00Z",
      "estimated_on": "2025-11-26T04:36:08Z",
      "actual_on": null,
      "scheduled_in": "2025-11-26T05:10:00Z",
      "estimated_in": "2025-11-26T04:46:08Z",
      "actual_in": null,
      "progress_percent": 91,
      "status": "En Route / On Time",
      "aircraft_type": "A332",
      "route_distance": 6188,
      "filed_airspeed": 465,
      "filed_altitude": null,
      "route": null,
      "baggage_claim": null,
      "seats_cabin_business": null,
      "seats_cabin_coach": null,
      "seats_cabin_first": null,
      "gate_origin": null,
      "gate_destination": null,
      "terminal_origin": null,
      "terminal_destination": "4S",
      "type": "Airline"
    },
    {
      "ident": "JAT763",
      "ident_icao": "JAT763",
      "ident_iata": "JA763",
      "actual_runway_off": "25",
      "actual_runway_on": "28",
      "fa_flight_id": "JAT763-1763877909-airline-1226p",
      "operator": "JAT",
      "operator_icao": "JAT",
      "operator_iata": "JA",
      "flight_number": "763",
      "registration": "CC-AWS",
      "atc_ident": null,
      "inbound_fa_flight_id": "JAT762-1763877909-airline-1224p",
      "codeshares": [],
      "codeshares_iata": [],
      "blocked": false,
      "diverted": false,
      "cancelled": false,
      "position_only": false,
      "origin": {
        "code": "SUMU",
        "code_icao": "SUMU",
        "code_iata": "MVD",
        "code_lid": null,
        "timezone": "America/Montevideo",
        "name": "Carrasco Int'l",
        "city": "Montevideo",
        "airport_info_url": "/airports/SUMU"
      },
      "destination": {
        "code": "SBGL",
        "code_icao": "SBGL",
        "code_iata": "GIG",
        "code_lid": null,
        "timezone": "America/Sao_Paulo",
        "name": "Rio de Janeiro/Galeao Intl",
        "city": "Rio de Janeiro",
        "airport_info_url": "/airports/SBGL"
      },
      "departure_delay": -480,
      "arrival_delay": 540,
      "filed_ete": 8580,
      "scheduled_out": "2025-11-25T17:07:00Z",
      "estimated_out": "2025-11-25T17:07:00Z",
      "actual_out": "2025-11-25T16:59:00Z",
      "scheduled_off": "2025-11-25T17:17:00Z",
      "estimated_off": "2025-11-25T17:13:11Z",
      "actual_off": "2025-11-25T17:13:11Z",
      "scheduled_on": "2025-11-25T19:40:00Z",
      "estimated_on": "2025-11-25T19:44:00Z",
      "actual_on": "2025-11-25T19:44:00Z",
      "scheduled_in": "2025-11-25T19:50:00Z",
      "estimated_in": "2025-11-25T19:31:00Z",
      "actual_in": "2025-11-25T19:59:00Z",
      "progress_percent": 100,
      "status": "Arrived / Gate Arrival",
      "aircraft_type": "A321",
      "route_distance": 1135,
      "filed_airspeed": 414,
      "filed_altitude": null,
      "route": null,
      "baggage_claim": null,
      "seats_cabin_business": null,
      "seats_cabin_coach": null,
      "seats_cabin_first": null,
      "gate_origin": null,
      "gate_destination": "C55",
      "terminal_origin": null,
      "terminal_destination": "2",
      "type": "Airline"
    },
    {
      "ident": "ARG1385",
      "ident_icao": "ARG1385",
      "ident_iata": "AR1385",
      "actual_runway_off": "25",
      "actual_runway_on": "13",
      "fa_flight_id": "ARG1385-1763884026-airline-925p",
      "operator": "ARG",
      "operator_icao": "ARG",
      "operator_iata": "AR",
      "flight_number": "1385",
      "registration": "LV-BYY",
      "atc_ident": null,
      "inbound_fa_flight_id": "ARG1384-1763884026-airline-924p",
      "codeshares": [
        "AFR3984"
      ],
      "codeshares_iata": [
        "AF3984"
      ],
      "blocked": false,
      "diverted": false,
      "cancelled": false,
      "position_only": false,
      "origin": {
        "code": "SUMU",
        "code_icao": "SUMU",
        "code_iata": "MVD",
        "code_lid": null,
        "timezone": "America/Montevideo",
        "name": "Carrasco Int'l",
        "city": "Montevideo",
        "airport_info_url": "/airports/SUMU"
      },
      "destination": {
        "code": "SABE",
        "code_icao": "SABE",
        "code_iata": "AEP",
        "code_lid": null,
        "timezone": "America/Argentina/Buenos_Aires",
        "name": "Jorge Newbery",
        "city": "Buenos Aires",
        "airport_info_url": "/airports/SABE"
      },
      "departure_delay": 420,
      "arrival_delay": 600,
      "filed_ete": 1380,
      "scheduled_out": "2025-11-25T16:35:00Z",
      "estimated_out": "2025-11-25T16:35:00Z",
      "actual_out": "2025-11-25T16:42:00Z",
      "scheduled_off": "2025-11-25T16:44:10Z",
      "estimated_off": "2025-11-25T16:55:02Z",
      "actual_off": "2025-11-25T16:55:02Z",
      "scheduled_on": "2025-11-25T17:07:10Z",
      "estimated_on": "2025-11-25T17:25:24Z",
      "actual_on": "2025-11-25T17:25:24Z",
      "scheduled_in": "2025-11-25T17:30:00Z",
      "estimated_in": "2025-11-25T17:36:00Z",
      "actual_in": "2025-11-25T17:40:00Z",
      "progress_percent": 100,
      "status": "Arrived / Gate Arrival",
      "aircraft_type": "B737",
      "route_distance": 137,
      "filed_airspeed": 195,
      "filed_altitude": null,
      "route": null,
      "baggage_claim": null,
      "seats_cabin_business": null,
      "seats_cabin_coach": null,
      "seats_cabin_first": null,
      "gate_origin": null,
      "gate_destination": null,
      "terminal_origin": null,
      "terminal_destination": null,
      "type": "Airline"
    },
    {
      "ident": "GLO7631",
      "ident_icao": "GLO7631",
      "ident_iata": "G37631",
      "actual_runway_off": "07",
      "actual_runway_on": "28L",
      "fa_flight_id": "GLO7631-1763879736-airline-1138p",
      "operator": "GLO",
      "operator_icao": "GLO",
      "operator_iata": "G3",
      "flight_number": "7631",
      "registration": "PS-GPL",
      "atc_ident": null,
      "inbound_fa_flight_id": "GLO7630-1763879736-airline-1137p",
      "codeshares": [
        "AAL7753",
        "ACA9833",
        "AFR6334",
        "AVA6401",
        "KLM9399",
        "THY9479",
        "UAE3734"
      ],
      "codeshares_iata": [
        "AA7753",
        "AC9833",
        "AF6334",
        "AV6401",
        "KL9399",
        "TK9479",
        "EK3734"
      ],
      "blocked": false,
      "diverted": false,
      "cancelled": false,
      "position_only": false,
      "origin": {
        "code": "SUMU",
        "code_icao": "SUMU",
        "code_iata": "MVD",
        "code_lid": null,
        "timezone": "America/Montevideo",
        "name": "Carrasco Int'l",
        "city": "Montevideo",
        "airport_info_url": "/airports/SUMU"
      },
      "destination": {
        "code": "SBGR",
        "code_icao": "SBGR",
        "code_iata": "GRU",
        "code_lid": null,
        "timezone": "America/Sao_Paulo",
        "name": "São Paulo-Guarulhos Int'l",
        "city": "Sao Paulo",
        "airport_info_url": "/airports/SBGR"
      },
      "departure_delay": 0,
      "arrival_delay": -14,
      "filed_ete": 7800,
      "scheduled_out": "2025-11-25T16:05:00Z",
      "estimated_out": "2025-11-25T16:05:00Z",
      "actual_out": null,
      "scheduled_off": "2025-11-25T16:15:00Z",
      "estimated_off": "2025-11-25T16:13:55Z",
      "actual_off": "2025-11-25T16:13:55Z",
      "scheduled_on": "2025-11-25T18:25:00Z",
      "estimated_on": "2025-11-25T18:25:33Z",
      "actual_on": "2025-11-25T18:25:33Z",
      "scheduled_in": "2025-11-25T18:35:00Z",
      "estimated_in": "2025-11-25T18:34:46Z",
      "actual_in": null,
      "progress_percent": 100,
      "status": "Arrived / Gate Arrival",
      "aircraft_type": "B38M",
      "route_distance": 977,
      "filed_airspeed": 392,
      "filed_altitude": null,
      "route": null,
      "baggage_claim": null,
      "seats_cabin_business": null,
      "seats_cabin_coach": null,
      "seats_cabin_first": null,
      "gate_origin": null,
      "gate_destination": null,
      "terminal_origin": null,
      "terminal_destination": "2",
      "type": "Airline"
    },
    {
      "ident": "AEA46",
      "ident_icao": "AEA46",
      "ident_iata": "UX46",
      "actual_runway_off": "07",
      "actual_runway_on": "32R",
      "fa_flight_id": "AEA46-1763878405-airline-106p",
      "operator": "AEA",
      "operator_icao": "AEA",
      "operator_iata": "UX",
      "flight_number": "46",
      "registration": "EC-OGY",
      "atc_ident": null,
      "inbound_fa_flight_id": "AEA45-1763792430-airline-1034p",
      "codeshares": [],
      "codeshares_iata": [],
      "blocked": false,
      "diverted": false,
      "cancelled": false,
      "position_only": false,
      "origin": {
        "code": "SUMU",
        "code_icao": "SUMU",
        "code_iata": "MVD",
        "code_lid": null,
        "timezone": "America/Montevideo",
        "name": "Carrasco Int'l",
        "city": "Montevideo",
        "airport_info_url": "/airports/SUMU"
      },
      "destination": {
        "code": "LEMD",
        "code_icao": "LEMD",
        "code_iata": "MAD",
        "code_lid": null,
        "timezone": "Europe/Madrid",
        "name": "Adolfo Suárez Madrid-Barajas",
        "city": "Madrid",
        "airport_info_url": "/airports/LEMD"
      },
      "departure_delay": -1260,
      "arrival_delay": -3720,
      "filed_ete": 37860,
      "scheduled_out": "2025-11-25T16:15:00Z",
      "estimated_out": "2025-11-25T16:15:00Z",
      "actual_out": "2025-11-25T15:54:00Z",
      "scheduled_off": "2025-11-25T16:25:00Z",
      "estimated_off": "2025-11-25T16:05:51Z",
      "actual_off": "2025-11-25T16:05:51Z",
      "scheduled_on": "2025-11-26T02:56:00Z",
      "estimated_on": "2025-11-26T02:53:50Z",
      "actual_on": "2025-11-26T02:53:50Z",
      "scheduled_in": "2025-11-26T04:05:00Z",
      "estimated_in": "2025-11-26T02:56:00Z",
      "actual_in": "2025-11-26T03:03:00Z",
      "progress_percent": 100,
      "status": "Arrived / Gate Arrival",
      "aircraft_type": "B789",
      "route_distance": 6188,
      "filed_airspeed": 468,
      "filed_altitude": null,
      "route": null,
      "baggage_claim": null,
      "seats_cabin_business": null,
      "seats_cabin_coach": null,
      "seats_cabin_first": null,
      "gate_origin": "4",
      "gate_destination": null,
      "terminal_origin": null,
      "terminal_destination": "1",
      "type": "Airline"
    },
    {
      "ident": "F595",
      "ident_icao": null,
      "ident_iata": null,
      "actual_runway_off": "07",
      "actual_runway_on": "19",
      "fa_flight_id": "F595-1764084771-adhoc-3186p",
      "operator": null,
      "operator_icao": null,
      "operator_iata": null,
      "flight_number": null,
      "registration": null,
      "atc_ident": null,
      "inbound_fa_flight_id": null,
      "codeshares": [],
      "codeshares_iata": [],
      "blocked": false,
      "diverted": false,
      "cancelled": false,
      "position_only": false,
      "origin": {
        "code": "SUMU",
        "code_icao": "SUMU",
        "code_iata": "MVD",
        "code_lid": null,
        "timezone": "America/Montevideo",
        "name": "Carrasco Int'l",
        "city": "Montevideo",
        "airport_info_url": "/airports/SUMU"
      },
      "destination": {
        "code": "SUMU",
        "code_icao": "SUMU",
        "code_iata": "MVD",
        "code_lid": null,
        "timezone": "America/Montevideo",
        "name": "Carrasco Int'l",
        "city": "Montevideo",
        "airport_info_url": "/airports/SUMU"
      },
      "departure_delay": 0,
      "arrival_delay": -4792,
      "filed_ete": 4792,
      "scheduled_out": null,
      "estimated_out": null,
      "actual_out": null,
      "scheduled_off": "2025-11-25T15:32:35Z",
      "estimated_off": "2025-11-25T15:32:35Z",
      "actual_off": "2025-11-25T15:32:35Z",
      "scheduled_on": "2025-11-25T16:52:27Z",
      "estimated_on": "2025-11-25T16:52:27Z",
      "actual_on": "2025-11-25T15:32:35Z",
      "scheduled_in": null,
      "estimated_in": null,
      "actual_in": null,
      "progress_percent": 100,
      "status": "Estimated arrival",
      "aircraft_type": null,
      "route_distance": 0,
      "filed_airspeed": null,
      "filed_altitude": null,
      "route": null,
      "baggage_claim": null,
      "seats_cabin_business": null,
      "seats_cabin_coach": null,
      "seats_cabin_first": null,
      "gate_origin": null,
      "gate_destination": null,
      "terminal_origin": null,
      "terminal_destination": null,
      "type": "General_Aviation"
    },
    {
      "ident": "N246ES",
      "ident_icao": null,
      "ident_iata": null,
      "actual_runway_off": "25",
      "actual_runway_on": "13",
      "fa_flight_id": "N246ES-1764082434-adhoc-1998p",
      "operator": null,
      "operator_icao": null,
      "operator_iata": null,
      "flight_number": null,
      "registration": "N246ES",
      "atc_ident": null,
      "inbound_fa_flight_id": "N246ES-1763749637-adhoc-1545p",
      "codeshares": [],
      "codeshares_iata": [],
      "blocked": false,
      "diverted": false,
      "cancelled": false,
      "position_only": false,
      "origin": {
        "code": "SUMU",
        "code_icao": "SUMU",
        "code_iata": "MVD",
        "code_lid": null,
        "timezone": "America/Montevideo",
        "name": "Carrasco Int'l",
        "city": "Montevideo",
        "airport_info_url": "/airports/SUMU"
      },
      "destination": {
        "code": "SABE",
        "code_icao": "SABE",
        "code_iata": "AEP",
        "code_lid": null,
        "timezone": "America/Argentina/Buenos_Aires",
        "name": "Jorge Newbery",
        "city": "Buenos Aires",
        "airport_info_url": "/airports/SABE"
      },
      "departure_delay": -480,
      "arrival_delay": 0,
      "filed_ete": 2107,
      "scheduled_out": null,
      "estimated_out": null,
      "actual_out": null,
      "scheduled_off": "2025-11-25T15:05:43Z",
      "estimated_off": "2025-11-25T15:05:43Z",
      "actual_off": "2025-11-25T14:57:43Z",
      "scheduled_on": "2025-11-25T15:40:50Z",
      "estimated_on": "2025-11-25T15:40:50Z",
      "actual_on": "2025-11-25T15:40:50Z",
      "scheduled_in": null,
      "estimated_in": null,
      "actual_in": null,
      "progress_percent": 100,
      "status": "Arrived",
      "aircraft_type": "C525",
      "route_distance": 137,
      "filed_airspeed": null,
      "filed_altitude": null,
      "route": null,
      "baggage_claim": null,
      "seats_cabin_business": null,
      "seats_cabin_coach": null,
      "seats_cabin_first": null,
      "gate_origin": null,
      "gate_destination": null,
      "terminal_origin": null,
      "terminal_destination": null,
      "type": "General_Aviation"
    },
    {
      "ident": "TAM8118",
      "ident_icao": "TAM8118",
      "ident_iata": "JJ8118",
      "actual_runway_off": "01",
      "actual_runway_on": "17L",
      "fa_flight_id": "TAM8118-1763878562-airline-90p",
      "operator": "TAM",
      "operator_icao": "TAM",
      "operator_iata": "JJ",
      "flight_number": "8118",
      "registration": "PT-MXG",
      "atc_ident": null,
      "inbound_fa_flight_id": "TAM8118-1763878562-airline-91p",
      "codeshares": [
        "LAN8118"
      ],
      "codeshares_iata": [
        "LA8118"
      ],
      "blocked": false,
      "diverted": false,
      "cancelled": false,
      "position_only": false,
      "origin": {
        "code": "SUMU",
        "code_icao": "SUMU",
        "code_iata": "MVD",
        "code_lid": null,
        "timezone": "America/Montevideo",
        "name": "Carrasco Int'l",
        "city": "Montevideo",
        "airport_info_url": "/airports/SUMU"
      },
      "destination": {
        "code": "SCEL",
        "code_icao": "SCEL",
        "code_iata": "SCL",
        "code_lid": null,
        "timezone": "America/Santiago",
        "name": "Comodoro Arturo Merino Benitez Int'l",
        "city": "Santiago",
        "airport_info_url": "/airports/SCEL"
      },
      "departure_delay": -840,
      "arrival_delay": -960,
      "filed_ete": 7860,
      "scheduled_out": "2025-11-25T14:35:00Z",
      "estimated_out": "2025-11-25T14:35:00Z",
      "actual_out": "2025-11-25T14:21:00Z",
      "scheduled_off": "2025-11-25T14:45:00Z",
      "estimated_off": "2025-11-25T14:35:00Z",
      "actual_off": "2025-11-25T14:31:29Z",
      "scheduled_on": "2025-11-25T16:56:00Z",
      "estimated_on": "2025-11-25T16:32:29Z",
      "actual_on": "2025-11-25T16:32:29Z",
      "scheduled_in": "2025-11-25T17:10:00Z",
      "estimated_in": "2025-11-25T16:41:00Z",
      "actual_in": "2025-11-25T16:54:00Z",
      "progress_percent": 100,
      "status": "Arrived / Gate Arrival",
      "aircraft_type": "A321",
      "route_distance": 850,
      "filed_airspeed": 329,
      "filed_altitude": null,
      "route": null,
      "baggage_claim": null,
      "seats_cabin_business": null,
      "seats_cabin_coach": null,
      "seats_cabin_first": null,
      "gate_origin": null,
      "gate_destination": null,
      "terminal_origin": null,
      "terminal_destination": "2",
      "type": "Airline"
    },
    {
      "ident": "CX-IPR",
      "ident_icao": null,
      "ident_iata": null,
      "actual_runway_off": "01",
      "actual_runway_on": "19",
      "fa_flight_id": "CXIPR-1764079460-adhoc-1015p",
      "operator": null,
      "operator_icao": null,
      "operator_iata": null,
      "flight_number": null,
      "registration": "CX-IPR",
      "atc_ident": null,
      "inbound_fa_flight_id": "CXIPR-1764073959-adhoc-0p",
      "codeshares": [],
      "codeshares_iata": [],
      "blocked": false,
      "diverted": false,
      "cancelled": false,
      "position_only": false,
      "origin": {
        "code": "SUMU",
        "code_icao": "SUMU",
        "code_iata": "MVD",
        "code_lid": null,
        "timezone": "America/Montevideo",
        "name": "Carrasco Int'l",
        "city": "Montevideo",
        "airport_info_url": "/airports/SUMU"
      },
      "destination": {
        "code": "SUMU",
        "code_icao": "SUMU",
        "code_iata": "MVD",
        "code_lid": null,
        "timezone": "America/Montevideo",
        "name": "Carrasco Int'l",
        "city": "Montevideo",
        "airport_info_url": "/airports/SUMU"
      },
      "departure_delay": 0,
      "arrival_delay": 0,
      "filed_ete": 4707,
      "scheduled_out": null,
      "estimated_out": null,
      "actual_out": null,
      "scheduled_off": "2025-11-25T14:04:14Z",
      "estimated_off": "2025-11-25T14:04:14Z",
      "actual_off": "2025-11-25T14:04:14Z",
      "scheduled_on": "2025-11-25T15:22:41Z",
      "estimated_on": "2025-11-25T15:22:41Z",
      "actual_on": "2025-11-25T15:22:41Z",
      "scheduled_in": null,
      "estimated_in": null,
      "actual_in": null,
      "progress_percent": 100,
      "status": "Arrived",
      "aircraft_type": null,
      "route_distance": 0,
      "filed_airspeed": null,
      "filed_altitude": null,
      "route": null,
      "baggage_claim": null,
      "seats_cabin_business": null,
      "seats_cabin_coach": null,
      "seats_cabin_first": null,
      "gate_origin": null,
      "gate_destination": null,
      "terminal_origin": null,
      "terminal_destination": null,
      "type": "General_Aviation"
    }
  ]
}